docs/.gitkeep
docs/index.md
docs/installation.md
docs/redoc.md
docs/assets/fonts/GoodSans-Medium.otf
docs/assets/fonts/GoodSans-MediumItalic.otf
docs/assets/fonts/GoodSans-Regular.otf
docs/assets/fonts/GoodSans-RegularItalic.otf
docs/assets/images/node.png
docs/client/api.md
docs/client/asset.md
docs/client/asset_collection.md
docs/client/geospatial.md
docs/client/model.md
docs/client/node.md
docs/client/record_collection.md
docs/client/run.md
docs/client/scenario.md
docs/client/technology.md
docs/data-coverage/power/assets.md
docs/data-coverage/power/generation.md
docs/data-coverage/steel/index.md
docs/stylesheets/extra.css
notebooks/.gitkeep
tests/.gitkeep
tests/__init__.py
tests/CI/__init__.py
tests/CI/conftest.py
tests/CI/test_api_aliases_get.py
tests/CI/test_api_provenance.py
tests/CI/test_api_records.py
tests/CI/test_api_technology.py
tests/CI/test_asset.py
tests/CI/test_asset_collection_construction.py
tests/CI/test_model.py
tests/CI/test_model_api.py
tests/CI/test_node.py
tests/CI/test_record.py
tests/CI/test_run.py
tests/CI/test_run_api.py
tests/CI/test_scenario.py
tests/CI/test_scenario_api.py
tests/CI/test_technology.py
tests/CI/fixtures/__init__.py
tests/CI/fixtures/api_aliases_get.py
tests/CI/fixtures/api_records_get.py
tz/client/__init__.py
tz/client/asset.py
tz/client/auth.py
tz/client/constants.py
tz/client/factory.py
tz/client/geospatial.py
tz/client/model.py
tz/client/node.py
tz/client/publisher.py
tz/client/record.py
tz/client/run.py
tz/client/scenario.py
tz/client/source.py
tz/client/technology.py
tz/client/utils.py
tz/client/api/__init__.py
tz/client/api/aliases.py
tz/client/api/assets.py
tz/client/api/base.py
tz/client/api/client.py
tz/client/api/constants.py
tz/client/api/geospatial.py
tz/client/api/models.py
tz/client/api/nodes.py
tz/client/api/publishers.py
tz/client/api/records.py
tz/client/api/runs.py
tz/client/api/scenarios.py
tz/client/api/schemas.py
tz/client/api/sources.py
tz/client/api/technologies.py
tz/client/cli/__init__.py
tz_client-0.0.5.dist-info/LICENSE
tz_client-0.0.5.dist-info/METADATA
tz_client-0.0.5.dist-info/WHEEL
tz_client-0.0.5.dist-info/entry_points.txt
tz_client-0.0.5.dist-info/top_level.txt
tz_client-0.0.5.dist-info/RECORD
